sleepfake/__init__.py
sleepfake/plugin.py
sleepfake-1.1.2.dist-info/WHEEL
sleepfake-1.1.2.dist-info/entry_points.txt
sleepfake-1.1.2.dist-info/METADATA
sleepfake-1.1.2.dist-info/RECORD
