Metadata-Version: 2.4
Name: sleepfake
Version: 1.1.2
Summary: Fake the time.sleep/asyncio.sleep function during tests.
Author: Guillaume Pouyat
Author-email: Guillaume Pouyat <guillaume.pouyat@protonmail.com>
License-Expression: MIT
Classifier: Development Status :: 5 - Production/Stable
Classifier: Programming Language :: Python
Classifier: Programming Language :: Python :: Implementation :: CPython
Classifier: Programming Language :: Python :: 3
Classifier: Programming Language :: Python :: 3 :: Only
Classifier: Programming Language :: Python :: 3.10
Classifier: Programming Language :: Python :: 3.11
Classifier: Programming Language :: Python :: 3.12
Classifier: Programming Language :: Python :: 3.13
Classifier: Intended Audience :: Developers
Classifier: License :: OSI Approved :: MIT License
Classifier: Topic :: Software Development :: Libraries :: Python Modules
Classifier: Topic :: Software Development :: Testing :: Mocking
Requires-Dist: freezegun>=1.4.0
Requires-Dist: pytest>=8.0.2
Requires-Python: >=3.10
